<?xml version="1.0" encoding="utf-8" standalone="yes" ?>
<T3locallang>
	<meta type="array">
		<description>Language labels for the FE plugin Filelist (dr_blob) used to localize the plugin configuration mask and the TCA-Fields</description>
		<type>module</type>
		<labelContext type="array">
			<label index="tx_drblob_content"></label>
			<label index="tx_drblob_content.title"></label>
			<label index="tx_drblob_content.description"></label>
			<label index="tx_drblob_content.type"></label>
			<label index="tx_drblob_content.type.db"></label>
			<label index="tx_drblob_content.type.fs"></label>
			<label index="tx_drblob_content.type.fsus"></label>
			<label index="tx_drblob_content.type.dam"></label>
			<label index="tx_drblob_content.cruser_id"></label>
			<label index="tx_drblob_content.crdate"></label>
			<label index="tx_drblob_content.tstamp"></label>
			<label index="tx_drblob_content.blob_name"></label>
			<label index="tx_drblob_content.blob_size"></label>
			<label index="tx_drblob_content.blob_type"></label>
			<label index="tx_drblob_content.blob_data"></label>
			<label index="tx_drblob_content.is_vip"></label>
			<label index="tx_drblob_content.is_vip.desc"></label>
			<label index="tx_drblob_content.download_count"></label>
			<label index="tx_drblob_content.download_count.desc"></label>
			<label index="tx_drblob_content.download_count.reset"></label>
			<label index="tx_drblob_content.category"></label>
			<label index="tx_drblob_category"></label>
			<label index="tx_drblob_category.title"></label>
			<label index="pages.folderIconsDescr"></label>
			<label index="tt_content.list_type_pi1"></label>
			<label index="tt_content.list_type_pi2"></label>
			<label index="tt_content.pi_flexform.sheet.datasource"></label>
			<label index="tt_content.pi_flexform.categories"></label>
			<label index="tt_content.pi_flexform.categories_mode"></label>
			<label index="tt_content.pi_flexform.categories_showAll"></label>
			<label index="tt_content.pi_flexform.categories_showSelected"></label>
			<label index="tt_content.pi_flexform.sheet.settings"></label>
			<label index="tt_content.pi_flexform.whatToDisplay"></label>
			<label index="tt_content.pi_flexform.whatToDisplay.top"></label>
			<label index="tt_content.pi_flexform.whatToDisplay.list"></label>
			<label index="tt_content.pi_flexform.whatToDisplay.single"></label>
			<label index="tt_content.pi_flexform.whatToDisplay.search"></label>
			<label index="tt_content.pi_flexform.whatToDisplay.personal_list"></label>
			<label index="tt_content.pi_flexform.whatToDisplay.dummy"></label>
			<label index="tt_content.pi_flexform.whatToDisplaypersonal.add"></label>
			<label index="tt_content.pi_flexform.limit"></label>
			<label index="tt_content.pi_flexform.listOrderBy"></label>
			<label index="tt_content.pi_flexform.listOrderBy.title"></label>
			<label index="tt_content.pi_flexform.listOrderBy.createdate"></label>
			<label index="tt_content.pi_flexform.listOrderBy.lastchange"></label>
			<label index="tt_content.pi_flexform.listOrderBy.author"></label>
			<label index="tt_content.pi_flexform.listOrderBy.sorting"></label>
			<label index="tt_content.pi_flexform.listOrderBy.download_count"></label>
			<label index="tt_content.pi_flexform.listOrderBy.blob_size"></label>
			<label index="tt_content.pi_flexform.listOrderBy.blob_name"></label>
			<label index="tt_content.pi_flexform.listOrderBy.blob_type"></label>
			<label index="tt_content.pi_flexform.listOrderDirection"></label>
			<label index="tt_content.pi_flexform.listOrderDirection.asc"></label>
			<label index="tt_content.pi_flexform.listOrderDirection.desc"></label>
			<label index="tt_content.pi_flexform.template_file"></label>
			<label index="tt_content.pi_flexform.template_subpart"></label>
			<label index="tt_content.pi_flexform.singlePID"></label>
			<label index="tt_content.pi_flexform.returnPID"></label>
		</labelContext>
	</meta>
	<data type="array">
		<languageKey index="default" type="array">
			<label index="tx_drblob_content">Download</label>
			<label index="tx_drblob_content.tab.general">General</label>
			<label index="tx_drblob_content.tab.visibility">Visibility</label>
			<label index="tx_drblob_content.title">Title</label>
			<label index="tx_drblob_content.description">Description</label>
			<label index="tx_drblob_content.type">Record storage type</label>
			<label index="tx_drblob_content.type.db">Store file in the Database (secure)</label>
			<label index="tx_drblob_content.type.fs">Store file in the Filesystem (secure)</label>
			<label index="tx_drblob_content.type.fsus">Store file in the Filesystem (unsecure)</label>
			<label index="tx_drblob_content.type.dam">Associate with a DAM file (unsecure)</label>
			<label index="tx_drblob_content.cruser_id">Author</label>
			<label index="tx_drblob_content.crdate">Create Date</label>
			<label index="tx_drblob_content.tstamp">Last Change</label>
			<label index="tx_drblob_content.blob_name">Filename</label>
			<label index="tx_drblob_content.blob_size">Filesize</label>
			<label index="tx_drblob_content.blob_type">Filetype</label>
			<label index="tx_drblob_content.blob_checksum">File Checksum</label>
			<label index="tx_drblob_content.blob_data">File</label>
			<label index="tx_drblob_content.is_vip">VIP-Record?</label>
			<label index="tx_drblob_content.is_vip.desc">Shall this record be shown in a vip-list?</label>
			<label index="tx_drblob_content.download_count">Downloadcounter</label>
			<label index="tx_drblob_content.download_count.desc">This file has been downloaded %s times</label>
			<label index="tx_drblob_content.download_count.reset">Reset Counter</label>
			<label index="tx_drblob_content.category">File categories</label>
			<label index="tx_drblob_category">File Category</label>
			<label index="tx_drblob_category.title">Title</label>
			<label index="pages.folderIconsDescr">Files</label>
			<label index="tt_content.list_type_pi1">Filelist</label>
			<label index="tt_content.list_type_pi2">Filelist</label>
			<label index="tt_content.pi_flexform.sheet.datasource">Data Source</label>
			<label index="tt_content.pi_flexform.sheet.settings">Settings</label>
			<label index="tt_content.pi_flexform.sheet.ds">Category selection</label>
			<label index="tt_content.pi_flexform.sheet.vFolderTree">&quot;vFolderTree&quot;-Settings</label>
			<label index="tt_content.pi_flexform.categories">Category selection:</label>
			<label index="tt_content.pi_flexform.categories_mode">Category mode:</label>
			<label index="tt_content.pi_flexform.categories_showAll">Show all (don't use selection below)</label>
			<label index="tt_content.pi_flexform.categories_showSelected">Show only categories selected below</label>
			<label index="tt_content.pi_flexform.categories_showSelected.and">Show only records that match all of the following categories (AND)</label>
			<label index="tt_content.pi_flexform.categories_showSelected.or">Show only records that match one of the following categories (OR)</label>
			<label index="tt_content.pi_flexform.vFolderTree_FolderSubscriptionMode">Folder Subscription Mode (Only necessary if personalize-option is set)</label>
			<label index="tt_content.pi_flexform.vFolderTree_FolderSubscriptionMode.all">Subscribe all folders of the vFolder tree</label>
			<label index="tt_content.pi_flexform.vFolderTree_FolderSubscriptionMode.selected">Subscribe only selected folder</label>
			<label index="tt_content.pi_flexform.whatToDisplay">What shall be displayed:</label>
			<label index="tt_content.pi_flexform.whatToDisplay.top">TOP (List of VIP-items)</label>
			<label index="tt_content.pi_flexform.whatToDisplay.list">LIST (List of items)</label>
			<label index="tt_content.pi_flexform.whatToDisplay.single">SINGLE (Single item)</label>
			<label index="tt_content.pi_flexform.whatToDisplay.search">SEARCH (Search items)</label>
			<label index="tt_content.pi_flexform.whatToDisplay.personal_list">PERSONAL (Personalizable list)</label>
			<label index="tt_content.pi_flexform.whatToDisplay.personal">PERSONAL (Personalizable list)</label>
			<label index="tt_content.pi_flexform.whatToDisplay.dummy">DUMMY (No Output)</label>
			<label index="tt_content.pi_flexform.whatToDisplaypersonal.add">Show &quot;Add to Personal Container&quot; (only in LIST-Mode):</label>
			<label index="tt_content.pi_flexform.showVFolderTree">Show the Virtual Folder Tree (only in LIST-Mode):</label>
			<label index="tt_content.pi_flexform.vFolderTreeInitialState">Initial State of the vFolder Tree:</label>
			<label index="tt_content.pi_flexform.vFolderTreeInitialState.all">Show the records of all folders</label>
			<label index="tt_content.pi_flexform.vFolderTreeInitialState.first">Show the records the first folder</label>
			<label index="tt_content.pi_flexform.vFolderTreeInitialState.none">Don't show any records initially</label>
			<label index="tt_content.pi_flexform.limit">Number of items to list:</label>
			<label index="tt_content.pi_flexform.usePageBrowser">Enable the PageBrowser for this list</label>
			<label index="tt_content.pi_flexform.listOrderBy">&quot;Order by&quot; this field:</label>
			<label index="tt_content.pi_flexform.listOrderBy.title">Title</label>
			<label index="tt_content.pi_flexform.listOrderBy.createdate">Date of the creation</label>
			<label index="tt_content.pi_flexform.listOrderBy.lastchange">Date of the last change</label>
			<label index="tt_content.pi_flexform.listOrderBy.author">Author</label>
			<label index="tt_content.pi_flexform.listOrderBy.sorting">Custom Backend Sorting</label>
			<label index="tt_content.pi_flexform.listOrderBy.download_count">Download Counter</label>
			<label index="tt_content.pi_flexform.listOrderBy.blob_name">Filename</label>
			<label index="tt_content.pi_flexform.listOrderBy.blob_size">Filesize</label>
			<label index="tt_content.pi_flexform.listOrderBy.blob_type">Mimetype</label>
			<label index="tt_content.pi_flexform.listOrderDirection">Ascending or Descending:</label>
			<label index="tt_content.pi_flexform.listOrderDirection.asc">Ascending</label>
			<label index="tt_content.pi_flexform.listOrderDirection.desc">Descending</label>
			<label index="tt_content.pi_flexform.template_file">Template file:</label>
			<label index="tt_content.pi_flexform.template_subpart">Template subpart:</label>
			<label index="tt_content.pi_flexform.singlePID">Page where to display single items:</label>
			<label index="tt_content.pi_flexform.returnPID">Page where to return to:</label>
			<label index="tt_content.pi_flexform.all.usets">Use TypoScript setting</label>
			<label index="tt_content.pi_flexform.all.no">No</label>
			<label index="tt_content.pi_flexform.all.yes">Yes</label>
		</languageKey>
		<languageKey index="de" type="array">
			<label index="tx_drblob_content">Download</label>
			<label index="tx_drblob_content.title">Titel</label>
			<label index="tx_drblob_content.description">Beschreibung</label>
			<label index="tx_drblob_content.type">Speichertyp Datensatz</label>
			<label index="tx_drblob_content.type.db">Datei in der Datenbank speichern</label>
			<label index="tx_drblob_content.type.fs">Datei im Dateisystem speichern</label>
			<label index="tx_drblob_content.type.dam">Datensatz mit DAM-Datei verknüpfen</label>
			<label index="tx_drblob_content.cruser_id">Autor</label>
			<label index="tx_drblob_content.crdate">Erstelldatum</label>
			<label index="tx_drblob_content.tstamp">Letzte Änderung</label>
			<label index="tx_drblob_content.blob_name">Dateiname</label>
			<label index="tx_drblob_content.blob_size">Dateigröße</label>
			<label index="tx_drblob_content.blob_type">Dateityp</label>
			<label index="tx_drblob_content.blob_checksum">Dateiprüfsumme</label>
			<label index="tx_drblob_content.blob_data">Datei auswählen</label>
			<label index="tx_drblob_content.is_vip">VIP-Datei?</label>
			<label index="tx_drblob_content.is_vip.desc">Soll der Datensatz in einer VIP-Liste aufgeführt werden?</label>
			<label index="tx_drblob_content.download_count">Downloadzähler</label>
			<label index="tx_drblob_content.download_count.desc">Diese Datei wurde bereits ###DOWNLOAD_COUNT### Mal heruntergeladen</label>
			<label index="tx_drblob_content.download_count.reset">Zähler zurücksetzen</label>
			<label index="tx_drblob_content.category">Dateikategorien</label>
			<label index="tx_drblob_category">Dateikategorie</label>
			<label index="tx_drblob_category.title">Titel</label>
			<label index="pages.folderIconsDescr">Dateien</label>
			<label index="tt_content.list_type_pi1">Dateiliste</label>
			<label index="tt_content.pi_flexform.sheet.datasource">Datenquelle</label>
			<label index="tt_content.pi_flexform.sheet.settings">Einstellungen</label>
			<label index="tt_content.pi_flexform.sheet.ds">Kategorieauswahl</label>
			<label index="tt_content.pi_flexform.sheet.vFolderTree">Ordnerbaum-Einstellungen</label>
			<label index="tt_content.pi_flexform.categories">Kategorieauswahl:</label>
			<label index="tt_content.pi_flexform.categories_mode">Kategorien anzeigen:</label>
			<label index="tt_content.pi_flexform.categories_showAll">Alle anzeigen (folgende Auswahl ignorieren)</label>
			<label index="tt_content.pi_flexform.categories_showSelected">Nur ausgewählte Kategorien anzeigen</label>
			<label index="tt_content.pi_flexform.whatToDisplay">Was soll angezeigt werden:</label>
			<label index="tt_content.pi_flexform.whatToDisplay.top">TOP: Liste bestehend aus VIP-Dokumenten</label>
			<label index="tt_content.pi_flexform.whatToDisplay.list">LIST: Liste aller Dokumente</label>
			<label index="tt_content.pi_flexform.whatToDisplay.single">SINGLE: Einzelnes Dokument</label>
			<label index="tt_content.pi_flexform.whatToDisplay.search">SEARCH: Suchen von Dokumenten</label>
			<label index="tt_content.pi_flexform.whatToDisplay.personal.list">PERSONAL: Personalisierbare Liste</label>
			<label index="tt_content.pi_flexform.whatToDisplaypersonal.add">&quot;Abonnieren&quot; anzeigen (nur im LIST-Modus):</label>
			<label index="tt_content.pi_flexform.showVFolderTree">Zeige virtuellen Ordnerbaum (nur im LIST-Modus):</label>
			<label index="tt_content.pi_flexform.limit">Anzahl an Listeneinträgen:</label>
			<label index="tt_content.pi_flexform.listOrderBy">&quot;Sortieren nach&quot; diesem Feld (nur im LIST-Modus):</label>
			<label index="tt_content.pi_flexform.listOrderBy.title">Titel</label>
			<label index="tt_content.pi_flexform.listOrderBy.createdate">Erstelldatum</label>
			<label index="tt_content.pi_flexform.listOrderBy.lastchange">Letzte Änderung</label>
			<label index="tt_content.pi_flexform.listOrderBy.author">Autor</label>
			<label index="tt_content.pi_flexform.listOrderBy.sorting">Benutzerdefinierte Backend-Sortierung</label>
			<label index="tt_content.pi_flexform.listOrderBy.blob_name">Dateiname</label>
			<label index="tt_content.pi_flexform.listOrderBy.blob_size">Dateigröße</label>
			<label index="tt_content.pi_flexform.listOrderBy.blob_type">MIME-Typ</label>
			<label index="tt_content.pi_flexform.listOrderDirection">Aufsteigend oder absteigend:</label>
			<label index="tt_content.pi_flexform.listOrderDirection.asc">Aufsteigend</label>
			<label index="tt_content.pi_flexform.listOrderDirection.desc">Absteigend</label>
			<label index="tt_content.pi_flexform.template_file">Vorlagendatei:</label>
			<label index="tt_content.pi_flexform.singlePID">Seite zur Anzeige einzelner Datensätze:</label>
			<label index="tt_content.pi_flexform.returnPID">Seite, zu der zurückgekehrt werden soll:</label>
		</languageKey>
		<languageKey index="es" type="array">
			<label index="tx_drblob_content">Fichero seguro</label>
			<label index="tx_drblob_content.title">Título</label>
			<label index="tx_drblob_content.description">Descripción</label>
			<label index="tx_drblob_content.type">Tipo de almacenamiento de resgistro</label>
			<label index="tx_drblob_content.type.db">Almacenar ficheros en la base de datos</label>
			<label index="tx_drblob_content.type.fs">Almacenar ficheros en el sistema de ficheros</label>
			<label index="tx_drblob_content.type.dam">Asociado con el fichero DAM</label>
			<label index="tx_drblob_content.cruser_id">Autor</label>
			<label index="tx_drblob_content.crdate">Datos creados</label>
			<label index="tx_drblob_content.tstamp">Último cambio</label>
			<label index="tx_drblob_content.blob_name">Nombre del fichero</label>
			<label index="tx_drblob_content.blob_size">Tamaño del fichero</label>
			<label index="tx_drblob_content.blob_type">Tipo de fichero</label>
			<label index="tx_drblob_content.blob_checksum">Fichero Checksum</label>
			<label index="tx_drblob_content.blob_data">Fichero</label>
			<label index="tx_drblob_content.is_vip">Registro VIP?</label>
			<label index="tx_drblob_content.is_vip.desc">Este registro deberá ser mostrado en una lista vip?</label>
			<label index="tx_drblob_content.download_count">Contador de descargas</label>
			<label index="tx_drblob_content.download_count.desc">El fichero ha sido descargado ###DOWNLOAD_COUNT###</label>
			<label index="tx_drblob_content.download_count.reset">Reiniciar el contador</label>
			<label index="tx_drblob_content.category">Categorías de ficheros</label>
			<label index="tx_drblob_category">Categoría de fichero</label>
			<label index="tx_drblob_category.title">Título</label>
			<label index="pages.folderIconsDescr">Ficheros</label>
			<label index="tt_content.list_type_pi1">Lista de ficheros</label>
			<label index="tt_content.pi_flexform.sheet.datasource">Fuente de datos</label>
			<label index="tt_content.pi_flexform.sheet.settings">Configuración</label>
			<label index="tt_content.pi_flexform.sheet.vFolderTree">&quot;vFolderTree &quot;-Ajustes</label>
			<label index="tt_content.pi_flexform.categories">Selección de categoria</label>
			<label index="tt_content.pi_flexform.categories_mode">Modo de categoría</label>
			<label index="tt_content.pi_flexform.categories_showAll">Mostrar todos (no utilizar la selección más adelante)</label>
			<label index="tt_content.pi_flexform.categories_showSelected">Mostrar únicamente las categorías seleccionadas a continuación</label>
			<label index="tt_content.pi_flexform.whatToDisplay">Qué se muestra</label>
			<label index="tt_content.pi_flexform.whatToDisplay.top">TOP: Lista de elementos-VIP</label>
			<label index="tt_content.pi_flexform.whatToDisplay.list">LISTA: Lista de elementos</label>
			<label index="tt_content.pi_flexform.whatToDisplay.single">ELEMENTO: Elemento individual</label>
			<label index="tt_content.pi_flexform.whatToDisplay.search">BÜSQUEDA: Búsqueda de elementos</label>
			<label index="tt_content.pi_flexform.whatToDisplay.personal.list">PERSONAL: lista personalizable</label>
			<label index="tt_content.pi_flexform.whatToDisplaypersonal.add">Mostrar &quot;Agregar a personal de contenedores&quot; (sólo en modo LISTA)</label>
			<label index="tt_content.pi_flexform.showVFolderTree">Mostrar árbol virtual de carpetas (sólo en modo LISTA)</label>
			<label index="tt_content.pi_flexform.limit">Número de elementos en la lista</label>
			<label index="tt_content.pi_flexform.listOrderBy">&quot;Ordenar por&quot; este campo (sólo en modo LISTA)</label>
			<label index="tt_content.pi_flexform.listOrderBy.title">Título</label>
			<label index="tt_content.pi_flexform.listOrderBy.createdate">Fecha de creación</label>
			<label index="tt_content.pi_flexform.listOrderBy.lastchange">Fecha del último cambio</label>
			<label index="tt_content.pi_flexform.listOrderBy.author">Autor</label>
			<label index="tt_content.pi_flexform.listOrderBy.sorting">Ordenacion personalizada en el backend</label>
			<label index="tt_content.pi_flexform.listOrderBy.blob_name">Nombre del fichero</label>
			<label index="tt_content.pi_flexform.listOrderBy.blob_size">Tamaño del fichero</label>
			<label index="tt_content.pi_flexform.listOrderBy.blob_type">Mimetype</label>
			<label index="tt_content.pi_flexform.listOrderDirection">Acendente o Descendente</label>
			<label index="tt_content.pi_flexform.listOrderDirection.asc">Ascendente</label>
			<label index="tt_content.pi_flexform.listOrderDirection.desc">Descendente</label>
			<label index="tt_content.pi_flexform.template_file">Fichero de plantilla</label>
			<label index="tt_content.pi_flexform.singlePID">Página donde se muestran los elementos individuales</label>
			<label index="tt_content.pi_flexform.returnPID">Página de retorno</label>
		</languageKey>
		<languageKey index="fi" type="array">
			<label index="tx_drblob_content">Tiedostosalaus</label>
			<label index="tx_drblob_content.title">Otsikko</label>
			<label index="tx_drblob_content.description">Kuvaus</label>
		</languageKey>
		<languageKey index="th" type="array">
			<label index="tx_drblob_content">Download</label>
			<label index="tx_drblob_content.title">ชื่อเรื่อง</label>
			<label index="tx_drblob_content.description">ลักษณะ</label>
			<label index="tx_drblob_content.type">ประเภทการจัดเก็บระเบียน</label>
			<label index="tx_drblob_content.type.db">เก็บแฟ้มในฐานข้อมูล (ปลอดภัย)</label>
			<label index="tx_drblob_content.type.fs">เก็บแฟ้มในระบบแฟ้ม (ปลอดภัย)</label>
			<label index="tx_drblob_content.type.fsus">เก็บแฟ้มในระบบแฟ้ม (unsecure)</label>
			<label index="tx_drblob_content.type.dam">เชื่อมโยงกับแฟ้ม DAM (unsecure)</label>
			<label index="tx_drblob_content.cruser_id">ผู้เขียน</label>
			<label index="tx_drblob_content.crdate">วันที่สร้าง</label>
			<label index="tx_drblob_content.tstamp">Last Change</label>
			<label index="tx_drblob_content.blob_name">ชื่อไฟล์</label>
			<label index="tx_drblob_content.blob_size">ขนาดของไฟล์</label>
			<label index="tx_drblob_content.blob_type">filetype</label>
			<label index="tx_drblob_content.blob_checksum">การตรวจสอบไฟล์</label>
			<label index="tx_drblob_content.blob_data">ไฟล์</label>
			<label index="tx_drblob_content.is_vip">VIP Record?</label>
			<label index="tx_drblob_content.is_vip.desc">บันทึกนี้จะแสดงในรายการ vip?</label>
			<label index="tx_drblob_content.download_count">Downloadcounter</label>
			<label index="tx_drblob_content.download_count.desc">ไฟล์นี้ถูกดาวน์โหลด s% ครั้ง</label>
			<label index="tx_drblob_content.download_count.reset">Counter Reset</label>
			<label index="tx_drblob_content.category">ประเภทไฟล์</label>
			<label index="tx_drblob_category">ประเภทไฟล์</label>
			<label index="tx_drblob_category.title">ชื่อเรื่อง</label>
			<label index="pages.folderIconsDescr">Files</label>
			<label index="tt_content.list_type_pi1">Filelist</label>
			<label index="tt_content.pi_flexform.sheet.datasource">แหล่งที่มา</label>
			<label index="tt_content.pi_flexform.sheet.settings">การตั้งค่า</label>
			<label index="tt_content.pi_flexform.sheet.vFolderTree">&quot;vFolderTree&quot;การตั้งค่า -</label>
			<label index="tt_content.pi_flexform.categories">เลือก Category :</label>
			<label index="tt_content.pi_flexform.categories_mode">โหมด Category :</label>
			<label index="tt_content.pi_flexform.categories_showAll">แสดงทั้งหมด (ไม่ได้ใช้การเลือกที่ด้านล่าง)</label>
			<label index="tt_content.pi_flexform.categories_showSelected">แสดงประเภทเท่านั้นที่เลือกด้านล่าง</label>
			<label index="tt_content.pi_flexform.categories_showSelected.and">ระเบียนแสดงเฉพาะที่ตรงกับประเภทดังต่อไปนี้ (และ)</label>
			<label index="tt_content.pi_flexform.categories_showSelected.or">แสดงรายการเท่านั้นที่ตรงกับประเภทดังต่อไปนี้ (OR)</label>
			<label index="tt_content.pi_flexform.vFolderTree_FolderSubscriptionMode">Folder Subscription Mode (เฉพาะหากจำเป็นตัวเลือก - ปรับตั้ง)</label>
			<label index="tt_content.pi_flexform.vFolderTree_FolderSubscriptionMode.all">Subscribe โฟลเดอร์ทั้งหมดของต้นไม้ vFolder</label>
			<label index="tt_content.pi_flexform.vFolderTree_FolderSubscriptionMode.selected">สมัครสมาชิกเพียงเลือกโฟลเดอร์</label>
			<label index="tt_content.pi_flexform.whatToDisplay">สิ่งที่จะต้องแสดง :</label>
			<label index="tt_content.pi_flexform.whatToDisplay.top">TOP (รายการ VIP รายการ)</label>
			<label index="tt_content.pi_flexform.whatToDisplay.list">รายชื่อ (List of items)</label>
			<label index="tt_content.pi_flexform.whatToDisplay.single">SINGLE (รายการ Single)</label>
			<label index="tt_content.pi_flexform.whatToDisplay.search">ค้นหา (Search รายการ)</label>
			<label index="tt_content.pi_flexform.whatToDisplay.personal_list">PERSONAL (รายการ Personalizable)</label>
			<label index="tt_content.pi_flexform.whatToDisplay.dummy">หลอก (Output No)</label>
			<label index="tt_content.pi_flexform.whatToDisplaypersonal.add">แสดง&quot;Add to Personal Container&quot;(เฉพาะในรายการ Mode) :</label>
			<label index="tt_content.pi_flexform.showVFolderTree">แสดง Virtual Folder Tree (เฉพาะ LIST - Mode) :</label>
			<label index="tt_content.pi_flexform.vFolderTreeInitialState">รัฐแรกของ vFolder Tree :</label>
			<label index="tt_content.pi_flexform.vFolderTreeInitialState.all">แสดงตำแหน่งของโฟลเดอร์ทั้งหมด</label>
			<label index="tt_content.pi_flexform.vFolderTreeInitialState.first">แสดงระเบียนที่โฟลเดอร์แรก</label>
			<label index="tt_content.pi_flexform.vFolderTreeInitialState.none">ไม่แสดงระเบียนใด ๆ ครั้งแรก</label>
			<label index="tt_content.pi_flexform.limit">จำนวนรายการในรายการ :</label>
			<label index="tt_content.pi_flexform.listOrderBy">&quot;Order by&quot;ข้อมูลนี้ :</label>
			<label index="tt_content.pi_flexform.listOrderBy.title">ชื่อเรื่อง</label>
			<label index="tt_content.pi_flexform.listOrderBy.createdate">วันที่สร้าง</label>
			<label index="tt_content.pi_flexform.listOrderBy.lastchange">วันที่เปลี่ยนแปลงล่าสุด</label>
			<label index="tt_content.pi_flexform.listOrderBy.author">ผู้เขียน</label>
			<label index="tt_content.pi_flexform.listOrderBy.sorting">Custom Backend Sorting</label>
			<label index="tt_content.pi_flexform.listOrderBy.download_count">Counter Download</label>
			<label index="tt_content.pi_flexform.listOrderBy.blob_name">Filename</label>
			<label index="tt_content.pi_flexform.listOrderBy.blob_size">ขนาดของไฟล์</label>
			<label index="tt_content.pi_flexform.listOrderBy.blob_type">Mimetype</label>
			<label index="tt_content.pi_flexform.listOrderDirection">หรือ Ascending Descending :</label>
			<label index="tt_content.pi_flexform.listOrderDirection.asc">Ascending</label>
			<label index="tt_content.pi_flexform.listOrderDirection.desc">Descending</label>
			<label index="tt_content.pi_flexform.template_file">แฟ้มแม่แบบ :</label>
			<label index="tt_content.pi_flexform.singlePID">หน้าเว็บที่แสดงรายการเดี่ยว</label>
			<label index="tt_content.pi_flexform.returnPID">หน้าที่เพื่อกลับไป :</label>
		</languageKey>
	</data>
	<orig_hash type="array">
	</orig_hash>
	<orig_text type="array">
	</orig_text>
</T3locallang>